alissimplemath-0.0.2.dist-info/licenses/LICENCE
alisson_simple_math/__init__.py
alisson_simple_math/adicao.py
alisson_simple_math/subtracao.py
alissimplemath-0.0.2.dist-info/METADATA
alissimplemath-0.0.2.dist-info/WHEEL
alissimplemath-0.0.2.dist-info/top_level.txt
alissimplemath-0.0.2.dist-info/RECORD
