Metadata-Version: 2.4
Name: alissimplemath
Version: 0.0.2
Summary: Um pacote simples de operações matemáticas para fins de aprendizado
Home-page: https://github.com/alissonguarnier/simple-package-template.git
Author: Alisson Guarniêr
Author-email: alisson.dfla@hotmail.com
Classifier: Programming Language :: Python :: 3
Classifier: License :: OSI Approved :: MIT License
Requires-Python: >=3.6
License-File: LICENCE
Dynamic: author
Dynamic: author-email
Dynamic: classifier
Dynamic: description
Dynamic: description-content-type
Dynamic: home-page
Dynamic: license-file
Dynamic: requires-python
Dynamic: summary
